rcmt/__init__.py
rcmt/action.py
rcmt/cli.py
rcmt/config.py
rcmt/context.py
rcmt/database/__init__.py
rcmt/database/migrations/README
rcmt/database/migrations/__init__.py
rcmt/database/migrations/env.py
rcmt/database/migrations/script.py.mako
rcmt/database/migrations/versions/1ebf5b1ca7fe_add_model_run.py
rcmt/database/migrations/versions/__init__.py
rcmt/database/migrations/versions/b3117b16eb76_add_model_extension.py
rcmt/filter.py
rcmt/fs.py
rcmt/git.py
rcmt/log.py
rcmt/metric.py
rcmt/py.typed
rcmt/rcmt.py
rcmt/source/__init__.py
rcmt/source/github.py
rcmt/source/gitlab.py
rcmt/source/local.py
rcmt/source/source.py
rcmt/task.py
rcmt/unittest.py
rcmt/util.py
rcmt/validate.py
rcmt/verify.py
rcmt-0.30.0.dist-info/LICENSE
rcmt-0.30.0.dist-info/METADATA
rcmt-0.30.0.dist-info/WHEEL
rcmt-0.30.0.dist-info/entry_points.txt
rcmt-0.30.0.dist-info/RECORD
