Metadata-Version: 2.1
Name: rcmt
Version: 0.30.0
Summary: 
Home-page: https://github.com/wndhydrnt/rcmt
License: MPL-2.0
Author: Markus Meyer
Author-email: hydrantanderwand@gmail.com
Requires-Python: >=3.9,<4.0
Classifier: Development Status :: 4 - Beta
Classifier: Environment :: Console
Classifier: Intended Audience :: Developers
Classifier: License :: OSI Approved
Classifier: License :: OSI Approved :: Mozilla Public License 2.0 (MPL 2.0)
Classifier: Programming Language :: Python :: 3
Classifier: Programming Language :: Python :: 3.9
Classifier: Programming Language :: Python :: 3.10
Classifier: Programming Language :: Python :: 3.11
Classifier: Programming Language :: Python :: 3.12
Requires-Dist: GitPython (>=3.1.18,<4.0.0)
Requires-Dist: PyGithub (>=2.0.0,<3.0.0)
Requires-Dist: PyYAML (>=5.4.1,<7.0.0)
Requires-Dist: alembic (>=1.8.1,<2.0.0)
Requires-Dist: click (>=8.0.1,<9.0.0)
Requires-Dist: greenlet (>=3.0.0,<4.0.0)
Requires-Dist: humanize (>=4.2.3,<5.0.0)
Requires-Dist: jinja2 (>=3.1.2,<4.0.0)
Requires-Dist: prometheus-client (>=0.19.0,<0.20.0)
Requires-Dist: pydantic (>=2.2.1,<3.0.0)
Requires-Dist: pydantic-settings (>=2.0.3,<3.0.0)
Requires-Dist: python-gitlab (>=4.2,<4.3)
Requires-Dist: python-slugify (>=7,<9)
Requires-Dist: sqlalchemy[mypy] (>=1.4.44,<3.0.0)
Requires-Dist: structlog (>=23.2,<23.3)
Project-URL: Changelog, https://github.com/wndhydrnt/rcmt/blob/main/CHANGELOG.md
Project-URL: Documentation, https://rcmt.readthedocs.io/
Project-URL: Repository, https://github.com/wndhydrnt/rcmt
